nifti_zarr-1.0.0rc5.dist-info/licenses/LICENSE
niizarr/__init__.py
niizarr/_compat.py
niizarr/_header.py
niizarr/_nii2zarr.py
niizarr/_units.py
niizarr/_version.py
niizarr/_zarr2nii.py
nifti_zarr-1.0.0rc5.dist-info/METADATA
nifti_zarr-1.0.0rc5.dist-info/WHEEL
nifti_zarr-1.0.0rc5.dist-info/entry_points.txt
nifti_zarr-1.0.0rc5.dist-info/top_level.txt
nifti_zarr-1.0.0rc5.dist-info/RECORD
