Metadata-Version: 2.4
Name: nifti-zarr
Version: 1.0.0rc5
Summary: Nifti-Zarr conversion tools in Python
Author-email: Yael Balbastre <y.balbastre@ucl.ac.uk>
Maintainer-email: Kaidong Chai <kchai1@mgh.harvard.edu>
License: MIT License
Project-URL: Homepage, https://github.com/neuroscales/nifti-zarr-py
Project-URL: Issues, https://github.com/neuroscales/nifti-zarr-py/issues
Classifier: License :: OSI Approved :: MIT License
Classifier: Operating System :: OS Independent
Classifier: Programming Language :: Python :: 3
Classifier: Intended Audience :: Science/Research
Requires-Python: >=3.8
License-File: LICENSE
Requires-Dist: zarr>=2
Requires-Dist: nibabel>=3
Requires-Dist: dask[array]>=2020
Requires-Dist: numpy>=1.18
Requires-Dist: numcodecs>=0.10.0
Requires-Dist: scikit-image>=0.19.2
Requires-Dist: packaging>=19.0
Provides-Extra: http
Requires-Dist: nibabel>=5; extra == "http"
Requires-Dist: fsspec[http]; extra == "http"
Provides-Extra: s3
Requires-Dist: nibabel>=5; extra == "s3"
Requires-Dist: fsspec[s3]; extra == "s3"
Provides-Extra: test
Requires-Dist: pooch; extra == "test"
Requires-Dist: jsonschema; extra == "test"
Requires-Dist: pytest; extra == "test"
Requires-Dist: jsondiff; extra == "test"
Dynamic: license-file
